fastapi_metabot/VERSION
fastapi_metabot/__init__.py
fastapi_metabot/models.py
fastapi_metabot/module.py
fastapi_metabot/routes.py
fastapi_metabot/utils.py
fastapi_metabot/client/__init__.py
fastapi_metabot/client/api_client.py
fastapi_metabot/client/exceptions.py
fastapi_metabot/client/models.py
fastapi_metabot/client/api/__init__.py
fastapi_metabot/client/api/metabot_api.py
fastapi_metabot-0.2.4.dist-info/METADATA
fastapi_metabot-0.2.4.dist-info/WHEEL
fastapi_metabot-0.2.4.dist-info/top_level.txt
fastapi_metabot-0.2.4.dist-info/RECORD
