Metadata-Version: 2.1
Name: fastapi-metabot
Version: 0.2.4
Summary: FastAPI plugin for quickly developing MetaBot modules
Home-page: https://github.com/vasyukvv42/metabot
Author: Vladislav Vasyuk
Author-email: vasyukvv42@gmail.com
License: MIT
Platform: UNKNOWN
Classifier: License :: OSI Approved :: MIT License
Classifier: Programming Language :: Python
Classifier: Programming Language :: Python :: 3
Classifier: Programming Language :: Python :: 3.8
Classifier: Programming Language :: Python :: Implementation :: CPython
Requires-Python: >=3.8.0
Requires-Dist: certifi (==2020.4.5.1)
Requires-Dist: chardet (==3.0.4)
Requires-Dist: fastapi (==0.54.1)
Requires-Dist: h11 (==0.9.0)
Requires-Dist: h2 (==3.2.0)
Requires-Dist: hpack (==3.0.0)
Requires-Dist: hstspreload (==2020.5.5)
Requires-Dist: httpx (==0.12.1)
Requires-Dist: hyperframe (==5.2.0)
Requires-Dist: idna (==2.9)
Requires-Dist: pydantic (==1.5.1)
Requires-Dist: rfc3986 (==1.4.0)
Requires-Dist: sniffio (==1.1.0)
Requires-Dist: starlette (==0.13.2)
Requires-Dist: typing-extensions (==3.7.4.2)
Requires-Dist: urllib3 (==1.25.9)
